NEMO_keycloak/__init__.py
NEMO_keycloak/app_settings.py
NEMO_keycloak/middleware.py
NEMO_keycloak/models.py
NEMO_keycloak/response.py
NEMO_keycloak/urls.py
NEMO_keycloak/views.py
NEMO_keycloak/admin/__init__.py
NEMO_keycloak/admin/realm.py
NEMO_keycloak/admin/server.py
NEMO_keycloak/auth/__init__.py
NEMO_keycloak/auth/backends.py
NEMO_keycloak/keycloak/__init__.py
NEMO_keycloak/keycloak/authz.py
NEMO_keycloak/keycloak/client.py
NEMO_keycloak/keycloak/exceptions.py
NEMO_keycloak/keycloak/mixins.py
NEMO_keycloak/keycloak/openid_connect.py
NEMO_keycloak/keycloak/realm.py
NEMO_keycloak/keycloak/uma.py
NEMO_keycloak/keycloak/uma1.py
NEMO_keycloak/keycloak/well_known.py
NEMO_keycloak/keycloak/admin/__init__.py
NEMO_keycloak/keycloak/admin/clientroles.py
NEMO_keycloak/keycloak/admin/clients.py
NEMO_keycloak/keycloak/admin/groups.py
NEMO_keycloak/keycloak/admin/realm.py
NEMO_keycloak/keycloak/admin/users.py
NEMO_keycloak/keycloak/admin/user/__init__.py
NEMO_keycloak/keycloak/admin/user/usergroup.py
NEMO_keycloak/keycloak/admin/user/userroles.py
NEMO_keycloak/keycloak/aio/__init__.py
NEMO_keycloak/keycloak/aio/abc.py
NEMO_keycloak/keycloak/aio/authz.py
NEMO_keycloak/keycloak/aio/client.py
NEMO_keycloak/keycloak/aio/mixins.py
NEMO_keycloak/keycloak/aio/openid_connect.py
NEMO_keycloak/keycloak/aio/realm.py
NEMO_keycloak/keycloak/aio/uma.py
NEMO_keycloak/keycloak/aio/well_known.py
NEMO_keycloak/management/__init__.py
NEMO_keycloak/management/commands/__init__.py
NEMO_keycloak/management/commands/keycloak_add_user.py
NEMO_keycloak/management/commands/keycloak_create_realm.py
NEMO_keycloak/management/commands/keycloak_refresh_realm.py
NEMO_keycloak/management/commands/keycloak_sync_resources.py
NEMO_keycloak/migrations/0001_initial.py
NEMO_keycloak/migrations/__init__.py
NEMO_keycloak/services/__init__.py
NEMO_keycloak/services/client.py
NEMO_keycloak/services/exceptions.py
NEMO_keycloak/services/oidc_profile.py
NEMO_keycloak/services/realm.py
NEMO_keycloak/services/uma.py
NEMO_keycloak-1.3.1.dist-info/LICENSE
NEMO_keycloak-1.3.1.dist-info/METADATA
NEMO_keycloak-1.3.1.dist-info/WHEEL
NEMO_keycloak-1.3.1.dist-info/top_level.txt
NEMO_keycloak-1.3.1.dist-info/RECORD
