Metadata-Version: 2.1
Name: NEMO-keycloak
Version: 1.3.1
Summary: Install Keycloak plugin for NEMO
Home-page: https://nemo.prometheuscomputing.com
Author: Prometheus Computing LLC
Author-email: nemo@prometheuscomputing.com
License: MIT
Keywords: NEMO,KEYCLOAK
Platform: UNKNOWN
Classifier: Development Status :: 4 - Beta
Classifier: Intended Audience :: Developers
Classifier: License :: OSI Approved :: MIT License
Classifier: Programming Language :: Python :: 3.6
Requires-Python: >=3.6
Requires-Dist: NEMO
Requires-Dist: python-jose
